eztea/__init__.py
eztea/__main__.py
eztea/clock.py
eztea/config.py
eztea/django/__init__.py
eztea/django/_router.py
eztea/django/_wsgi.py
eztea/django/request.py
eztea/django/testing.py
eztea/falcon/__init__.py
eztea/falcon/_app.py
eztea/falcon/_router.py
eztea/falcon/request.py
eztea/falcon/testing.py
eztea/json.py
eztea/sql/__init__.py
eztea/sql/_cli.py
eztea/sql/_connection.py
eztea/sql/_schema.py
eztea/sql/_timing.py
eztea/sql/migration/__init__.py
eztea/sql/migration/_command.py
eztea/sql/migration/_directory.py
eztea/sql/migration/_env_py.py
eztea/sql/migration/_error.py
eztea/sql/migration/_ignore_tables.py
eztea/sql/migration/template/alembic.ini
eztea/sql/migration/template/env.py.txt
eztea/sql/migration/template/script.py.mako
eztea/sql/sqltypes.py
eztea/web/__init__.py
eztea/web/_helper.py
eztea/web/_mimetype.py
eztea/web/_request.py
eztea/web/_router.py
eztea/web/_signature.py
eztea/web/_testing.py
eztea/web/error.py
eztea-0.1.12.dist-info/METADATA
eztea-0.1.12.dist-info/WHEEL
eztea-0.1.12.dist-info/entry_points.txt
eztea-0.1.12.dist-info/RECORD
